btrack_beat_tracker.so
btrack_beat_tracker-1.0.7.dist-info/METADATA
btrack_beat_tracker-1.0.7.dist-info/WHEEL
btrack_beat_tracker-1.0.7.dist-info/RECORD
