Metadata-Version: 2.2
Name: btrack-beat-tracker
Version: 1.0.7
Summary: Python bindings for the BTrack beat tracker
Author: Adam Stark
License: GPLv3
Requires-Python: >=3.8
